kt17py/__init__.py
kt17py/_kt17.cpython-36m-darwin.so
kt17py/kt17.py
kt17py-0.0.2.dist-info/LICENSE
kt17py-0.0.2.dist-info/METADATA
kt17py-0.0.2.dist-info/WHEEL
kt17py-0.0.2.dist-info/top_level.txt
kt17py-0.0.2.dist-info/RECORD
