Metadata-Version: 2.1
Name: kt17py
Version: 0.0.2
Summary: A Python wrapper to the FORTRAN code for the KT17 dynamic magnetic field model for Mercury's magnetosphere
Home-page: https://github.com/inaki-ortizdelandaluce/kt17py
Author: Inaki Ortiz de Landaluce
Author-email: inaki.ortizdelandaluce@gmail.com
License: MIT
Platform: UNKNOWN
Classifier: Programming Language :: Python :: 3
Classifier: License :: OSI Approved :: MIT License
Requires-Python: >=2.7
Requires-Dist: numpy (>=1.16)
